{
    "font": {
        "line-height": {
            "$value": 1.7,
            "$type": "number"
        },
        "family": {
            "$value": ["Lora", "serif"],
            "$type": "fontFamily"
        }
    },
    "color": {
        "base": {
            "$description": "Primitive color palette consisting of raw values and numeric scales.",
            "grey": {
                "$description": "Anchor Hue: 247.9 (Cool Neutral)",
                "100": {
                    "$value": {
                        "colorSpace": "oklch",
                        "components": [0.9433, 0.0055, 247.9],
                        "alpha": 1
                    },
                    "$type": "color"
                },
                "200": {
                    "$value": {
                        "colorSpace": "oklch",
                        "components": [0.9291, 0.0069, 247.9],
                        "alpha": 1
                    },
                    "$type": "color"
                }
            },
            "space-grey": {
                "$description": "Anchor Hue: 253.5 (Deep Slate)",
                "100": {
                    "$value": {
                        "colorSpace": "oklch",
                        "components": [0.5608, 0.0351, 253.57],
                        "alpha": 1
                    },
                    "$type": "color"
                },
                "200": {
                    "$value": {
                        "colorSpace": "oklch",
                        "components": [0.3829, 0.0222, 253.55],
                        "alpha": 1
                    },
                    "$type": "color"
                },
                "300": {
                    "$value": {
                        "colorSpace": "oklch",
                        "components": [0.1797, 0.007, 253.45],
                        "alpha": 1
                    },
                    "$type": "color"
                }
            },
            "green": {
                "$description": "Anchor Hue: 159.2 (Brand Green)",
                "100": {
                    "$value": {
                        "colorSpace": "oklch",
                        "components": [0.9066, 0.0459, 159.22],
                        "alpha": 1
                    },
                    "$type": "color"
                },
                "200": {
                    "$value": {
                        "colorSpace": "oklch",
                        "components": [0.6011, 0.1146, 158.95],
                        "alpha": 1
                    },
                    "$type": "color"
                },
                "300": {
                    "$value": {
                        "colorSpace": "oklch",
                        "components": [0.4882, 0.0909, 159.22],
                        "alpha": 1
                    },
                    "$type": "color"
                }
            },
            "cream": {
                "$description": "Anchor Hue: 88.6 (Warm Parchment)",
                "100": {
                    "$value": {
                        "colorSpace": "oklch",
                        "components": [0.985, 0.002, 88.64],
                        "alpha": 1
                    },
                    "$type": "color"
                },
                "200": {
                    "$value": {
                        "colorSpace": "oklch",
                        "components": [0.9733, 0.007, 88.64],
                        "alpha": 1
                    },
                    "$type": "color"
                }
            },
            "purple": {
                "$description": "Alternate brand accent palette.",
                "100": {
                    "$value": {
                        "colorSpace": "oklch",
                        "components": [0.8537, 0.0592, 299.296],
                        "alpha": 1
                    },
                    "$type": "color"
                },
                "200": {
                    "$value": {
                        "colorSpace": "oklch",
                        "components": [0.5291, 0.1493, 295.43],
                        "alpha": 1
                    },
                    "$type": "color"
                },
                "300": {
                    "$value": {
                        "colorSpace": "oklch",
                        "components": [0.2446, 0.0474, 297.52],
                        "alpha": 1
                    },
                    "$type": "color"
                }
            }
        },
        "text": {
            "$description": "Semantic tokens for text content, defining hierarchy and intent.",
            "primary": {
                "$value": "{color.base.space-grey.200}",
                "$type": "color",
                "$description": "Standard color for body text."
            },
            "secondary": {
                "$value": "{color.base.space-grey.100}",
                "$type": "color",
                "$description": "Subtle text used for dates, metadata, and secondary information."
            },
            "heading": {
                "$value": "{color.base.space-grey.300}",
                "$type": "color",
                "$description": "High-contrast color for headings and primary interactive elements."
            },
            "inverse": {
                "$value": "{color.base.cream.100}",
                "$type": "color",
                "$description": "Light text color for use on dark backgrounds."
            },
            "accent": {
                "$value": "{color.base.green.300}",
                "$type": "color",
                "$description": "Brand accent color for specific text highlights."
            },
            "accent-alt": {
                "$value": "{color.base.purple.300}",
                "$type": "color",
                "$description": "Alternate brand accent color for text highlights."
            }
        },
        "bg": {
            "$description": "Semantic tokens for background colors, defining UI layers and states.",
            "page": {
                "$value": "{color.base.cream.200}",
                "$type": "color",
                "$description": "Foundation background color for the entire viewport."
            },
            "surface": {
                "$value": "{color.base.cream.100}",
                "$type": "color",
                "$description": "Background for elevated UI surfaces like article cards and containers."
            },
            "subtle": {
                "$value": "{color.base.grey.100}",
                "$type": "color",
                "$description": "Very light background used for zebra-striping and hover states."
            },
            "accent": {
                "$value": "{color.base.green.200}",
                "$type": "color",
                "$description": "Primary brand color for high-visibility backgrounds and banners."
            },
            "accent-subtle": {
                "$value": "{color.base.green.100}",
                "$type": "color",
                "$description": "Faint brand tint used for soft highlights, like inline link backgrounds."
            },
            "accent-alt": {
                "$value": "{color.base.purple.200}",
                "$type": "color",
                "$description": "Alternate brand color for high-visibility backgrounds."
            },
            "accent-alt-subtle": {
                "$value": "{color.base.purple.100}",
                "$type": "color",
                "$description": "Faint alternate brand tint for soft highlights."
            }
        },
        "border": {
            "$description": "Semantic tokens for borders and dividers.",
            "subtle": {
                "$value": "{color.base.space-grey.100}",
                "$type": "color",
                "$description": "Low-contrast border color for blockquotes and subtle dividers."
            },
            "accent-alt": {
                "$value": "{color.base.purple.200}",
                "$type": "color",
                "$description": "Alternate brand accent border color."
            }
        },
        "icon": {
            "$description": "Semantic tokens for icons and SVG fills.",
            "primary": {
                "$value": "{color.base.green.200}",
                "$type": "color",
                "$description": "Standard brand color for icons."
            },
            "secondary": {
                "$value": "{color.base.green.300}",
                "$type": "color",
                "$description": "Darker brand color for hovered or active icon states."
            },
            "inverse": {
                "$value": "{color.base.cream.100}",
                "$type": "color",
                "$description": "Light icon color for use on dark backgrounds."
            }
        }
    },
    "size": {
        "container": {
            "$value": {
                "value": 50,
                "unit": "rem"
            },
            "$type": "dimension"
        },
        "gutter": {
            "$value": {
                "value": 4.75,
                "unit": "rem"
            },
            "$type": "dimension"
        }
    },
    "radius": {
        "md": {
            "$value": {
                "value": 8,
                "unit": "px"
            },
            "$type": "dimension"
        },
        "sm": {
            "$value": {
                "value": 2,
                "unit": "px"
            },
            "$type": "dimension"
        }
    },
    "spacing": {
        "xl": {
            "$value": {
                "value": 3,
                "unit": "rem"
            },
            "$type": "dimension"
        },
        "lg": {
            "$value": {
                "value": 1.5,
                "unit": "rem"
            },
            "$type": "dimension"
        },
        "md": {
            "$value": {
                "value": 1,
                "unit": "rem"
            },
            "$type": "dimension"
        },
        "sm": {
            "$value": {
                "value": 0.5,
                "unit": "rem"
            },
            "$type": "dimension"
        }
    },
    "shadow": {
        "card": {
            "$type": "shadow",
            "$value": {
                "offsetX": {
                    "value": 0,
                    "unit": "px"
                },
                "offsetY": {
                    "value": 1,
                    "unit": "px"
                },
                "blur": {
                    "value": 3,
                    "unit": "px"
                },
                "spread": {
                    "value": 0,
                    "unit": "px"
                },
                "color": {
                    "colorSpace": "srgb",
                    "components": [0, 0, 0],
                    "alpha": 0.15
                }
            }
        },
        "accent": {
            "$type": "shadow",
            "$value": {
                "offsetX": {
                    "value": 2,
                    "unit": "px"
                },
                "offsetY": {
                    "value": 2,
                    "unit": "px"
                },
                "blur": {
                    "value": 0,
                    "unit": "px"
                },
                "spread": {
                    "value": 0,
                    "unit": "px"
                },
                "color": "{color.bg.accent}"
            }
        }
    }
}
